{
	"namespace": {
		"SD": {
			"kind": "motif",
			"color": "#ff9e17",
			"matrix": [
				{
					"A": 1,
					"C": 0,
					"G": 0,
					"T": 0
				},
				{
					"A": 0,
					"C": 0,
					"G": 1,
					"T": 0
				},
				{
					"A": 0,
					"C": 0,
					"G": 1,
					"T": 0
				},
				{
					"A": 1,
					"C": 0,
					"G": 0,
					"T": 0
				},
				{
					"A": 0,
					"C": 0,
					"G": 1,
					"T": 0
				},
				{
					"A": 0,
					"C": 0,
					"G": 1,
					"T": 0
				}
			]
		}
	},
	"background": {
		"A": 0.25,
		"C": 0.25,
		"G": 0.25,
		"T": 0.25
	},
	"alphabet": [
		"A",
		"C",
		"G",
		"T"
	],
	"root": [
		{
			"kind": "element",
			"name": "SD"
		}
	]
}